nameko_serializer/__init__.py
nameko_serializer/serializer.py
nameko_serializer-1.0.0.dist-info/LICENSE.md
nameko_serializer-1.0.0.dist-info/METADATA
nameko_serializer-1.0.0.dist-info/WHEEL
nameko_serializer-1.0.0.dist-info/entry_points.txt
nameko_serializer-1.0.0.dist-info/top_level.txt
nameko_serializer-1.0.0.dist-info/zip-safe
nameko_serializer-1.0.0.dist-info/RECORD
