Metadata-Version: 2.1
Name: nameko-serializer
Version: 1.0.0
Summary: nameko serializer compatible with datetime and namedtuple
Home-page: https://github.com/Yupeek/nameko-serializer
Author: Darius BERNARD
Author-email: darius@yupeek.com
License: GPL3
Keywords: nameko json serializer namedtuple datetime
Platform: UNKNOWN
Classifier: Development Status :: 4 - Beta
Classifier: Intended Audience :: Developers
Classifier: License :: OSI Approved :: GNU General Public License v3 (GPLv3)
Classifier: Programming Language :: Python :: 2
Classifier: Programming Language :: Python :: 2.7
Classifier: Programming Language :: Python :: 3
Classifier: Programming Language :: Python :: 3.6
Classifier: Programming Language :: Python :: 3.7
Classifier: Operating System :: OS Independent
Classifier: Topic :: Software Development :: Libraries
Classifier: Topic :: Utilities
Requires-Dist: tzlocal
Requires-Dist: pytz
